{
  "ComponentAllowCustomization": true,
  "ComponentChangedSinceFileImport": true,
  "ComponentManifest": {
    "AllowAccessToGlobals": false,
    "AllowCustomization": true,
    "Description": "",
    "Name": "CMenu",
    "TemplateGuid": "ce50b1b24d104fb480bfe5dcd755c2e2"
  },
  "ComponentType": "CanvasComponent",
  "CustomGroupControlTemplateName": "",
  "CustomProperties": [],
  "FirstParty": true,
  "Id": "http://microsoft.com/appmagic/Component",
  "IsComponentLocked": false,
  "IsComponentTemplate": true,
  "IsCustomGroupControlTemplate": false,
  "IsPcfControl": false,
  "IsPremiumPcfControl": false,
  "IsWidgetTemplate": false,
  "LastModifiedTimestamp": "638026433102524347",
  "Name": "ce50b1b24d104fb480bfe5dcd755c2e2",
  "OverridableProperties": {},
  "Version": "638024509970117865"
}